{
  "Trigger": {
    "center": {
      "x": 93.31794,
      "y": 854.7111
    },
    "radius": 25.0,
    "rotation": 0.0,
    "wire_thickness": 0.0,
    "scale_x": 1.0,
    "scale_y": 1.0,
    "is_timer_enabled": false,
    "timer_interval": 32,
    "material": "",
    "surface": "",
    "is_visible": false,
    "is_enabled": true,
    "hit_height": 150.0,
    "name": "TriggerLF1",
    "shape": "none",
    "anim_speed": 1.0,
    "is_reflection_enabled": false,
    "drag_points": [
      {
        "x": 99.30192,
        "y": 835.5037,
        "z": 0.0,
        "smooth": true,
        "is_slingshot": false,
        "has_auto_texture": true,
        "tex_coord": 0.0,
        "is_locked": false,
        "editor_layer": 0,
        "editor_layer_name": "",
        "editor_layer_visibility": true
      },
      {
        "x": 81.76081,
        "y": 855.94916,
        "z": 0.0,
        "smooth": true,
        "is_slingshot": false,
        "has_auto_texture": true,
        "tex_coord": 0.0,
        "is_locked": false,
        "editor_layer": 0,
        "editor_layer_name": "",
        "editor_layer_visibility": true
      },
      {
        "x": 78.10658,
        "y": 869.4726,
        "z": 0.0,
        "smooth": false,
        "is_slingshot": false,
        "has_auto_texture": true,
        "tex_coord": 0.0,
        "is_locked": false,
        "editor_layer": 0,
        "editor_layer_name": "",
        "editor_layer_visibility": true
      },
      {
        "x": 124.525955,
        "y": 874.45123,
        "z": 0.0,
        "smooth": false,
        "is_slingshot": false,
        "has_auto_texture": true,
        "tex_coord": 0.0,
        "is_locked": false,
        "editor_layer": 0,
        "editor_layer_name": "",
        "editor_layer_visibility": true
      },
      {
        "x": 79.903915,
        "y": 888.54913,
        "z": 0.0,
        "smooth": false,
        "is_slingshot": false,
        "has_auto_texture": true,
        "tex_coord": 0.0,
        "is_locked": false,
        "editor_layer": 0,
        "editor_layer_name": "",
        "editor_layer_visibility": true
      },
      {
        "x": 135.34557,
        "y": 990.5826,
        "z": 0.0,
        "smooth": false,
        "is_slingshot": false,
        "has_auto_texture": true,
        "tex_coord": 0.0,
        "is_locked": false,
        "editor_layer": 0,
        "editor_layer_name": "",
        "editor_layer_visibility": true
      },
      {
        "x": 139.41623,
        "y": 997.2199,
        "z": 0.0,
        "smooth": true,
        "is_slingshot": false,
        "has_auto_texture": true,
        "tex_coord": 0.0,
        "is_locked": false,
        "editor_layer": 0,
        "editor_layer_name": "",
        "editor_layer_visibility": true
      },
      {
        "x": 144.34087,
        "y": 1004.35944,
        "z": 0.0,
        "smooth": true,
        "is_slingshot": false,
        "has_auto_texture": true,
        "tex_coord": 0.0,
        "is_locked": false,
        "editor_layer": 0,
        "editor_layer_name": "",
        "editor_layer_visibility": true
      },
      {
        "x": 158.70908,
        "y": 1015.4924,
        "z": 0.0,
        "smooth": true,
        "is_slingshot": false,
        "has_auto_texture": true,
        "tex_coord": 0.0,
        "is_locked": false,
        "editor_layer": 0,
        "editor_layer_name": "",
        "editor_layer_visibility": true
      },
      {
        "x": 177.40758,
        "y": 1018.201,
        "z": 0.0,
        "smooth": true,
        "is_slingshot": false,
        "has_auto_texture": true,
        "tex_coord": 0.0,
        "is_locked": false,
        "editor_layer": 0,
        "editor_layer_name": "",
        "editor_layer_visibility": true
      },
      {
        "x": 208.3204,
        "y": 1004.20905,
        "z": 0.0,
        "smooth": true,
        "is_slingshot": false,
        "has_auto_texture": true,
        "tex_coord": 0.0,
        "is_locked": false,
        "editor_layer": 0,
        "editor_layer_name": "",
        "editor_layer_visibility": true
      },
      {
        "x": 231.49667,
        "y": 986.0007,
        "z": 0.0,
        "smooth": true,
        "is_slingshot": false,
        "has_auto_texture": true,
        "tex_coord": 0.0,
        "is_locked": false,
        "editor_layer": 0,
        "editor_layer_name": "",
        "editor_layer_visibility": true
      },
      {
        "x": 244.33156,
        "y": 972.7947,
        "z": 0.0,
        "smooth": true,
        "is_slingshot": false,
        "has_auto_texture": true,
        "tex_coord": 0.0,
        "is_locked": false,
        "editor_layer": 0,
        "editor_layer_name": "",
        "editor_layer_visibility": true
      },
      {
        "x": 259.65546,
        "y": 949.1846,
        "z": 0.0,
        "smooth": true,
        "is_slingshot": false,
        "has_auto_texture": true,
        "tex_coord": 0.0,
        "is_locked": false,
        "editor_layer": 0,
        "editor_layer_name": "",
        "editor_layer_visibility": true
      },
      {
        "x": 265.43774,
        "y": 932.095,
        "z": 0.0,
        "smooth": true,
        "is_slingshot": false,
        "has_auto_texture": true,
        "tex_coord": 0.0,
        "is_locked": false,
        "editor_layer": 0,
        "editor_layer_name": "",
        "editor_layer_visibility": true
      },
      {
        "x": 267.83142,
        "y": 918.7487,
        "z": 0.0,
        "smooth": true,
        "is_slingshot": false,
        "has_auto_texture": true,
        "tex_coord": 0.0,
        "is_locked": false,
        "editor_layer": 0,
        "editor_layer_name": "",
        "editor_layer_visibility": true
      },
      {
        "x": 264.2937,
        "y": 906.2703,
        "z": 0.0,
        "smooth": true,
        "is_slingshot": false,
        "has_auto_texture": true,
        "tex_coord": 0.0,
        "is_locked": false,
        "editor_layer": 0,
        "editor_layer_name": "",
        "editor_layer_visibility": true
      },
      {
        "x": 255.60379,
        "y": 895.14874,
        "z": 0.0,
        "smooth": true,
        "is_slingshot": false,
        "has_auto_texture": true,
        "tex_coord": 0.0,
        "is_locked": false,
        "editor_layer": 0,
        "editor_layer_name": "",
        "editor_layer_visibility": true
      },
      {
        "x": 244.14339,
        "y": 888.6903,
        "z": 0.0,
        "smooth": false,
        "is_slingshot": false,
        "has_auto_texture": true,
        "tex_coord": 0.0,
        "is_locked": false,
        "editor_layer": 0,
        "editor_layer_name": "",
        "editor_layer_visibility": true
      },
      {
        "x": 139.9914,
        "y": 830.3405,
        "z": 0.0,
        "smooth": false,
        "is_slingshot": false,
        "has_auto_texture": true,
        "tex_coord": 0.0,
        "is_locked": false,
        "editor_layer": 0,
        "editor_layer_name": "",
        "editor_layer_visibility": true
      },
      {
        "x": 131.6891,
        "y": 828.13074,
        "z": 0.0,
        "smooth": true,
        "is_slingshot": false,
        "has_auto_texture": true,
        "tex_coord": 0.0,
        "is_locked": false,
        "editor_layer": 0,
        "editor_layer_name": "",
        "editor_layer_visibility": true
      },
      {
        "x": 118.22646,
        "y": 828.18054,
        "z": 0.0,
        "smooth": true,
        "is_slingshot": false,
        "has_auto_texture": true,
        "tex_coord": 0.0,
        "is_locked": false,
        "editor_layer": 0,
        "editor_layer_name": "",
        "editor_layer_visibility": true
      }
    ]
  }
}